casbin_couchbase_adapter/__init__.py
casbin_couchbase_adapter/adapter.py
casbin_couchbase_adapter-0.2.0.data/data/README.md
casbin_couchbase_adapter-0.2.0.dist-info/LICENSE.md
casbin_couchbase_adapter-0.2.0.dist-info/METADATA
casbin_couchbase_adapter-0.2.0.dist-info/WHEEL
casbin_couchbase_adapter-0.2.0.dist-info/top_level.txt
casbin_couchbase_adapter-0.2.0.dist-info/RECORD
