Metadata-Version: 2.1
Name: casbin_couchbase_adapter
Version: 0.2.0
Summary: Couchbase Adapter for PyCasbin
Home-page: https://github.com/ScienceLogic/casbin-couchbase-adapter
Author: ScienceLogic
License: Apache2
Keywords: casbin,Couchbase,casbin-adapter,rbac,access control,abac,acl,permission
Classifier: Programming Language :: Python :: 3.5
Classifier: Programming Language :: Python :: 3.6
Classifier: Programming Language :: Python :: 3.7
Classifier: License :: OSI Approved :: Apache Software License
Classifier: Operating System :: OS Independent
Requires-Python: >=3.5
License-File: LICENSE.md
Requires-Dist: casbin>=0.8.4
Requires-Dist: couchbase<=5.0.0,>=4.1.2
Requires-Dist: decorator>=4.4.2
Requires-Dist: py>=1.10.0
Requires-Dist: retry==0.9.2
Requires-Dist: simpleeval>=0.9.11
